flexi_config/__init__.py
flexi_config/aws_secrets.py
flexi_config/config.py
flexi_config-1.0.4.dist-info/METADATA
flexi_config-1.0.4.dist-info/WHEEL
flexi_config-1.0.4.dist-info/top_level.txt
flexi_config-1.0.4.dist-info/RECORD
