Metadata-Version: 2.1
Name: flexi-config
Version: 1.0.4
Summary: Flexible config objects utilizing AWS Secrets Manager
Home-page: https://github.com/leantaas/flexi_config
Author: LeanTaaS
Author-email: ryan.b@leantaas.com
License: UNKNOWN
Platform: UNKNOWN
Requires-Python: >=3.6
Requires-Dist: requests (>=2.3.0)
Requires-Dist: six (>=1.10.0)
Requires-Dist: boto3 (>=1.9.231)
Requires-Dist: botocore (>=1.12.231)
Requires-Dist: docutils (>=0.15.2)
Requires-Dist: jmespath (>=0.9.4)
Requires-Dist: python-dateutil (>=2.8.0)
Requires-Dist: PyYAML (>=5.1.2)
Requires-Dist: s3transfer (>=0.2.1)
Requires-Dist: six (>=1.12.0)
Requires-Dist: urllib3 (>=1.25.3)
